README.md
setup.py
busrt_async/__init__.py
busrt_async/client.py
busrt_async/rpc.py
busrt_async.egg-info/PKG-INFO
busrt_async.egg-info/SOURCES.txt
busrt_async.egg-info/dependency_links.txt
busrt_async.egg-info/top_level.txt