Metadata-Version: 2.1
Name: busrt-async
Version: 0.1.2
Summary: Python client for BUS/RT (async)
Home-page: https://github.com/alttch/busrt
Author: Bohemia Automation / Altertech
Author-email: div@altertech.com
License: MIT
Platform: UNKNOWN
Classifier: Programming Language :: Python :: 3
Classifier: License :: OSI Approved :: MIT License
Classifier: Topic :: Software Development :: Libraries
Classifier: Topic :: Communications
